peaktools/__init__.py
peaktools/plugins/__init__.py
peaktools/plugins/isotope.cp36-win_amd64.pyd
peaktools/plugins/utils.cp36-win_amd64.pyd
peaktools/samples/isotope/data/20200709_LM2_Fetuin_DIA_IGP_library120619_Glycan_Composition.txt
peaktools/samples/isotope/param/param_peaktools_isotope_v20210907.txt
peaktools-0.0.0.dist-info/LICENSE
peaktools-0.0.0.dist-info/METADATA
peaktools-0.0.0.dist-info/WHEEL
peaktools-0.0.0.dist-info/entry_points.txt
peaktools-0.0.0.dist-info/top_level.txt
peaktools-0.0.0.dist-info/RECORD
