Metadata-Version: 2.1
Name: peaktools
Version: 0.0.0
Summary: PeakTools: tools for proteomics analysis
Home-page: UNKNOWN
Author: Yingwei Hu
Author-email: yhu39@jhmi.edu
License: MIT
Platform: UNKNOWN
